giz/__init__.py
giz-1.0.0.dist-info/LICENSE
giz-1.0.0.dist-info/METADATA
giz-1.0.0.dist-info/WHEEL
giz-1.0.0.dist-info/entry_points.txt
giz-1.0.0.dist-info/RECORD
