Metadata-Version: 2.1
Name: giz
Version: 1.0.0
Summary: Drop in `git commit` replacement with AI commit message.
Author: Jake Zuliani
Author-email: jake@burla.dev
Requires-Python: >=3.10,<4.0
Classifier: Programming Language :: Python :: 3
Classifier: Programming Language :: Python :: 3.10
Classifier: Programming Language :: Python :: 3.11
Requires-Dist: openai (>=1.0,<2.0)
Requires-Dist: platformdirs (>=4.4.0,<5.0.0)
Requires-Dist: typer (>=0.17.3,<0.18.0)
Requires-Dist: yaspin (>=3.1.0,<4.0.0)
